CHANGES.txt
README.txt
setup.py
archetypes/__init__.py
archetypes.markerfield.egg-info/PKG-INFO
archetypes.markerfield.egg-info/SOURCES.txt
archetypes.markerfield.egg-info/dependency_links.txt
archetypes.markerfield.egg-info/namespace_packages.txt
archetypes.markerfield.egg-info/not-zip-safe
archetypes.markerfield.egg-info/requires.txt
archetypes.markerfield.egg-info/top_level.txt
archetypes/markerfield/__init__.py
archetypes/markerfield/field.py
archetypes/markerfield/utils.py
archetypes/markerfield/tests/__init__.py
archetypes/markerfield/tests/testUtils.py