Metadata-Version: 1.0
Name: archetypes.markerfield
Version: 1.1
Summary: Interface marker field for Archetypes
Home-page: UNKNOWN
Author: Wichert Akkertman
Author-email: wichert@wiggy.net
License: ZPL
Platform: UNKNOWN
Classifier: Framework :: Zope2
Classifier: Framework :: Plone
Classifier: Intended Audience :: Developers
Classifier: License :: OSI Approved :: Zope Public License
Classifier: Programming Language :: Python
